accessor/__init__.py
python_accessor-1.0.2.dist-info/licenses/LICENSE
python_accessor-1.0.2.dist-info/METADATA
python_accessor-1.0.2.dist-info/WHEEL
python_accessor-1.0.2.dist-info/top_level.txt
python_accessor-1.0.2.dist-info/RECORD
