Metadata-Version: 2.4
Name: python-accessor
Version: 1.0.2
Summary: Access nested dicts
Author-email: Jakub Jagielka <jjagielka@gmail.com>
License-Expression: MIT AND (Apache-2.0 OR BSD-2-Clause)
Project-URL: Homepage, https://github.com/jjagielka/python-accessor
Project-URL: Issues, https://github.com/jjagielka/python-accessor/issues
Project-URL: Repository, https://github.com/jjagielka/python-accessor
Keywords: accessor,api,itemgetter,rest
Classifier: Development Status :: 5 - Production/Stable
Classifier: Operating System :: OS Independent
Classifier: Programming Language :: Python
Classifier: Topic :: Software Development :: Libraries :: Python Modules
Requires-Python: >=3.10
License-File: LICENSE
Dynamic: license-file
